{
  "timestamp": "2025-12-17T21:58:56.564Z",
  "services": [
    {
      "name": "Main Platform",
      "key": "main",
      "status": "up",
      "responseTime": 530,
      "statusCode": 200
    },
    {
      "name": "ChatGroups",
      "key": "chatgroups",
      "status": "up",
      "responseTime": 428,
      "statusCode": 200
    },
    {
      "name": "Directory",
      "key": "directory",
      "status": "up",
      "responseTime": 517,
      "statusCode": 200
    },
    {
      "name": "GentlePulse",
      "key": "gentlepulse",
      "status": "up",
      "responseTime": 522,
      "statusCode": 200
    },
    {
      "name": "Chyme",
      "key": "chyme",
      "status": "up",
      "responseTime": 555,
      "statusCode": 200
    },
    {
      "name": "Default Alive or Dead",
      "key": "default-alive-or-dead",
      "status": "up",
      "responseTime": 585,
      "statusCode": 200
    },
    {
      "name": "Workforce Recruiter",
      "key": "workforce-recruiter",
      "status": "up",
      "responseTime": 696,
      "statusCode": 200
    },
    {
      "name": "LightHouse",
      "key": "lighthouse",
      "status": "up",
      "responseTime": 621,
      "statusCode": 200
    },
    {
      "name": "LostMail",
      "key": "lostmail",
      "status": "up",
      "responseTime": 690,
      "statusCode": 200
    },
    {
      "name": "MechanicMatch",
      "key": "mechanicmatch",
      "status": "up",
      "responseTime": 734,
      "statusCode": 200
    },
    {
      "name": "CompareNotes",
      "key": "research",
      "status": "up",
      "responseTime": 697,
      "statusCode": 200
    },
    {
      "name": "SocketRelay",
      "key": "socketrelay",
      "status": "up",
      "responseTime": 691,
      "statusCode": 200
    },
    {
      "name": "SupportMatch",
      "key": "supportmatch",
      "status": "up",
      "responseTime": 859,
      "statusCode": 200
    },
    {
      "name": "TrustTransport",
      "key": "trusttransport",
      "status": "up",
      "responseTime": 801,
      "statusCode": 200
    }
  ],
  "overall": {
    "total": 14,
    "up": 14,
    "down": 0
  }
}